{
  "concept_id": "C50918",
  "concept_name": "BBU",
  "category": "AI 伺服器",
  "note": "備援電池模組，受惠資料中心電力備援需求",
  "source_url": "https://www.cmoney.tw/forum/concept/C50918",
  "fetched_at": "2026-07-14 05:02:50",
  "article_count": 36,
  "articles": [
    {
      "id": "180719023",
      "title": "6月營收亮眼，光寶、台達電、崇越及矽力杰2Q營收達成率全破百",
      "text": "台股AI供應鏈6月營收全面報捷，四大標的第二季達成率破百。台達電656億元（+55.4%YoY），高瓦數電源放量，散熱L2A全年預估年增80%；光寶科187億元（+37%YoY），達成率102.4%，高階PSU、800VDC陸續放量；崇越75億元（+32.9%YoY），AI產品占比升至30%，7月起調漲光阻液與FOUP價格；矽力杰上半年年增25.5%，達發光通訊動能強勁。AI電源、散熱與半導體材料族群結構性成長動能延續，為台股中報行情最具續航力主軸。\n\n一、台股焦點：AI供應鏈6月營收繳亮眼成績單\n\n二、台達電：6月營收656.03億元（+11.3%MoM、+55.4%YoY）\n\n三、光寶科：6月營收186.56億元（+7.5%MoM、+37%YoY）\n\n四、崇越：6月營收75.07億元（+14.8%MoM、+32.9%YoY）\n\n五、矽力＊-KY（矽力杰）：6月營收20.84億元（+37.77%YoY）\n\n六、達發：6月營收22.10億元（+14.4%YoY）",
      "summary": "台股AI供應鏈6月營收全面報捷，四大標的第二季達成率破百。台達電656億元（+55.4%YoY），高瓦數電源放量，散熱L2A全年預估年增80%；光寶科187億元（+37%YoY），達成率102.4%，高階PSU、800VDC陸續放量；崇越75億元（+32.9%YoY），AI產品占比升至30%，7月起調漲光阻液與FOUP...",
      "time": "2026-07-13 18:30",
      "modify_time": "2026-07-13 18:30",
      "stocks": [
        "TWA00",
        "2308",
        "2301",
        "6526",
        "6415"
      ],
      "comment_count": 1,
      "like_count": 37,
      "laugh_count": 0,
      "money_count": 0,
      "shock_count": 0,
      "think_count": 0,
      "collected_count": 1,
      "url": "https://www.cmoney.tw/forum/article/180719023"
    },
    {
      "id": "180705134",
      "title": "這算W底嗎，還是不是這樣看的",
      "text": "這算W底嗎，還是不是這樣看的",
      "summary": "這算W底嗎，還是不是這樣看的",
      "time": "2026-07-13 10:56",
      "modify_time": "2026-07-13 10:56",
      "stocks": [
        "3211"
      ],
      "comment_count": 4,
      "like_count": 9,
      "laugh_count": 0,
      "money_count": 0,
      "shock_count": 0,
      "think_count": 0,
      "collected_count": 1,
      "url": "https://www.cmoney.tw/forum/article/180705134"
    },
    {
      "id": "180725981",
      "title": "AI貨櫃式液冷散熱方案 首座20呎正式導入日本",
      "text": "給台達<優秀經營團隊>按讚！\n\n從台達液冷散熱方案正式導入日本首座20呎AI貨櫃式資料中心【 談 關鍵意涵 】\n\n                先談結論\n這個 20 呎 AI 貨櫃不是實驗，而是高單價、高利潤的商品進入收割期。對客戶來說是「降本增效」，對台達來說是「營收結構占半壁江山、毛利率高標化的質變。」\n\n壹：前言\n導入 20 呎 AI 貨櫃式資料中心對「客戶與「台達公司本身」而言，是雙贏的商業模式。\n它不僅解決了客戶在 AI 算力\n大爆發時代的痛點，更將台達的營收規模與毛利表現推向全新的高度。\n\n以下為雙方優勢及對財務營收毛利量化與質化的解析：\n\n一.對客戶的優勢:快.省.高彈性\n對於急需算力的企業（如日本 Mirait One、雲端服務商）而言，傳統蓋一座 AI 資料中心要花費 1 到 2 年，而貨櫃式方案將帶來了根本性的改變：\n①縮短建置期數週內完成部署\n②極佳的節能效率：相較於傳統資料中心，每年能幫客戶省下高達 30% 以上的巨額電費\n③高密度與靈活部署：極度適合邊緣運算（Edge AI）或地皮昂貴的市區據點（如東京）\n\n二、對台達的優勢：\n  從「賣零件到賣系統整合」\n①產品單價（ASP）將暴增 \n出一案頂過去上萬件零組訂單\n\n②將形成高度生態系壁壘：台達能做到 Grid-to-Chip（從電網到晶片）的一條龍整合，並整合智慧管理軟體（DCIM），\n這種「高軟硬體集成度」讓對手很難單純用價格戰來搶單。\n\n③營收與毛利率將會大幅提升\n  A：2026 年下半年隨著更多   \n   20 呎貨櫃商用合約導入， \n   高毛利的基礎設施與系統整\n   合財，將確保台達整體毛利\n   率常態性維持在 36% 以上的 \n   超高水準。\n  B：營收及獲利貢獻 隨 20 呎\n  貨櫃與模組化資料中心等大型  \n  專案陸續在海外開花結果AI資\n  料中心業務2026年估將達 \n  50%以上且獲利將倍增。\n\n         以上淺見提供參考 \n相信公司 一起加油 Jine 7/14",
      "summary": "給台達<優秀經營團隊>按讚！ 從台達液冷散熱方案正式導入日本首座20呎AI貨櫃式資料中心【 談 關鍵意涵 】 先談結論 這個 20 呎 AI 貨櫃不是實驗，而是高單價、高利潤的商品進入收割期。對客戶來說是「降本增效」，對台達來說是「營收結構占半壁江山、毛利率高標化的質變。」 壹：前言 導入 20 呎 AI 貨櫃式資料中...",
      "time": "2026-07-14 04:09",
      "modify_time": "2026-07-14 04:10",
      "stocks": [
        "2308"
      ],
      "comment_count": 0,
      "like_count": 2,
      "laugh_count": 0,
      "money_count": 0,
      "shock_count": 0,
      "think_count": 0,
      "collected_count": 1,
      "url": "https://www.cmoney.tw/forum/article/180725981"
    },
    {
      "id": "180723003",
      "title": "就是有！所以不用急！",
      "text": "2026/5/11\n金寶大整合 打造ODM艦隊專訪\n=>HVDC 產品，預期何時發酵？\n答:重點要看GPU什麼時候準備好，我們認為，2027年底到2028年才會開始比較大規模的正式量產。\n\n由康舒設計、對接客戶，實際的試產與量產則放在泰金寶…......\n\n/////////////////////////////////////////\n今天早上2026.07.13  09:12\n黃仁勳粉碎Rubin Ultra延期傳聞\n明確表示Rubin Ultra的開發進度依然符合預期，將於明年如期出貨。\n\n關鍵技術模組如800V供電與機架間的光學互連技術，皆按原定計畫推進，次世代產品周期並未受到干擾。\n\n////////////////////////////////////////\n2026/7/6\nNvdia通知HVDC Q3準時量產（ABB伙伴=康舒）\n\n所以不用急\n87%確定是羅賓了！BBU他們也自己來（納入一條龍），試產到量產都在泰金寶，Q4再多一個量子電腦和ai伺服器進入系統組合測試\n\n有！就是有！所以不用急！！",
      "summary": "2026/5/11 金寶大整合 打造ODM艦隊專訪 =>HVDC 產品，預期何時發酵？ 答:重點要看GPU什麼時候準備好，我們認為，2027年底到2028年才會開始比較大規模的正式量產。 由康舒設計、對接客戶，實際的試產與量產則放在泰金寶…...... /////////////////////////////////...",
      "time": "2026-07-13 22:14",
      "modify_time": "2026-07-13 22:14",
      "stocks": [
        "9105",
        "2312",
        "6282",
        "2324"
      ],
      "comment_count": 12,
      "like_count": 120,
      "laugh_count": 0,
      "money_count": 0,
      "shock_count": 0,
      "think_count": 1,
      "collected_count": 2,
      "url": "https://www.cmoney.tw/forum/article/180723003"
    },
    {
      "id": "180672494",
      "title": "台達電放眼：未來2~3年   股價 飛越 3000元可預見",
      "text": "TO：台達股東  ( Part 4 )\n靜待~7月底官方法說會\n\n壹：超前推估(Q2)財務指標  \n① Q2 合併營收(已確定）\n 1,832.56億元直接改寫台達\n 創立以來單季歷史新高紀錄\n② Q2 預估毛利率將調升\n  越 36%以上，預估將落在 \n 36.5% ～ 37.5% 的高水準\n 推估理由：6 月產品組合中， \n 電源及零組件高達 50%、基礎\n 設施佔 37%。這意味著毛利最\n 高的 AI 伺服器高壓電GB30平 \n 台與液冷 CDU 出貨佔了絕對\n 統治地位。\n 加上近日傳出台達電因應上游 \n 材料全面啟動第二波漲價（漲\n 幅達 5%~20%）規模經濟與漲\n 價效應將強力拉高毛利表現\n\n③ Q2預估單季稅後淨利將衝\n    上 330億 ～ 355 億元新高\n\n④ Q2 預估單季 EPS:依股本 \n   膨脹係數估算Q2單季 EPS \n   有望高達 $8.6 ～ $9.2 元\n\n⑤ 加上Q1爆發的 7.91 元 光是 2026上半年台達電就已經狂賺近 17 元(約 16.51~17.11 元)\n\n⑥ 2026 全年將賺進近4個股本  \n    (EPS 37~45元) 是可期待的\n\n貳：重申推估未來2~3年股價\n一、 2026年 大成長年\n  * 全年稅後淨利【破仟億元】\n    AI液冷與GB300利潤兌現\n    達陣 2,400元~2500+元\n二、2027年 強勁爆發年\n  * 全年營收【躍兆元】\n    800V高壓配電系統全面普及  \n    跨越 2,600元~2700+元\n三、2028年大豐收年\n  * 全年 EPS【越100+元】\n    車用與微電網獲利正式接棒    \n    飛躍 2,800元~3000+元\n\n 以上提供參考 Jine 7/10 晚",
      "summary": "TO：台達股東 ( Part 4 ) 靜待~7月底官方法說會 壹：超前推估(Q2)財務指標 ① Q2 合併營收(已確定） 1,832.56億元直接改寫台達 創立以來單季歷史新高紀錄 ② Q2 預估毛利率將調升 越 36%以上，預估將落在 36.5% ～ 37.5% 的高水準 推估理由：6 月產品組合中， 電源及零組件高...",
      "time": "2026-07-10 16:55",
      "modify_time": "2026-07-10 20:45",
      "stocks": [
        "2308"
      ],
      "comment_count": 5,
      "like_count": 51,
      "laugh_count": 0,
      "money_count": 1,
      "shock_count": 0,
      "think_count": 0,
      "collected_count": 3,
      "url": "https://www.cmoney.tw/forum/article/180672494"
    },
    {
      "id": "179852608",
      "title": "阿達正傳",
      "text": "1.速馬達老師（大學體育老師）每個交易日09:30前，都會提供當天大盤頸線（也有稱為多空分歧點、強弱關鍵…名稱很多，意思一樣），供大家參考。感謝他的幫忙，所以就以阿達為名，取代其他複雜的名稱。\n2.藉由觀察阿達，大致就能知道當天大盤走勢：大盤守住阿達，大盤指數會比較正向，尤其是大盤在阿婆之上，守住阿達助漲抗跌；大盤不守阿達，縱使漲也會受限，萬一大盤是在阿婆之下，會跌的很有感覺。\n3.很多金融商品也都有阿達，例如股票個股每天也都有阿達，只是個股礙於短沖、成交量…，有時連午盤都還出現新的阿達，然個股阿達在實務上仍具ㄧ定參考價值，大家有空可以試著觀察。\n您愛阿達嗎？如果可以，麻煩看到速馬達每天提供阿達部位時，不吝跟他按個讚，有空也可留言跟他畫畫虎蘭。",
      "summary": "1.速馬達老師（大學體育老師）每個交易日09:30前，都會提供當天大盤頸線（也有稱為多空分歧點、強弱關鍵…名稱很多，意思一樣），供大家參考。感謝他的幫忙，所以就以阿達為名，取代其他複雜的名稱。 2.藉由觀察阿達，大致就能知道當天大盤走勢：大盤守住阿達，大盤指數會比較正向，尤其是大盤在阿婆之上，守住阿達助漲抗跌；大盤不守...",
      "time": "2026-06-13 14:03",
      "modify_time": "2026-06-13 14:03",
      "stocks": [
        "TWA00",
        "00631L",
        "00632R",
        "6282",
        "6770"
      ],
      "comment_count": 35,
      "like_count": 176,
      "laugh_count": 0,
      "money_count": 1,
      "shock_count": 0,
      "think_count": 0,
      "collected_count": 18,
      "url": "https://www.cmoney.tw/forum/article/179852608"
    },
    {
      "id": "180720475",
      "title": "🌟 7/14（明日）當沖觀察標的分享",
      "text": "明日當沖關注清單\n3374精材\n6182合晶\n3211順達\n4958臻鼎-KY\n8150南茂\n6683雍智\n\n以上個股將持續觀察開盤後的量價變化、盤勢強弱與主力動向，尋找短線交易機會。\n\n⚠️【風險提醒】\n當沖交易波動較大，本文僅為個人觀察與市場資訊分享，並非買賣建議。投資前請務必做好研究，嚴格執行停損與資金控管，盈虧需自行承擔。\n\n有興趣一起研究個股、交流盤勢看法的朋友，歡迎留言討論！",
      "summary": "明日當沖關注清單 3374精材 6182合晶 3211順達 4958臻鼎-KY 8150南茂 6683雍智 以上個股將持續觀察開盤後的量價變化、盤勢強弱與主力動向，尋找短線交易機會。 ⚠️【風險提醒】 當沖交易波動較大，本文僅為個人觀察與市場資訊分享，並非買賣建議。投資前請務必做好研究，嚴格執行停損與資金控管，盈虧需自...",
      "time": "2026-07-13 20:04",
      "modify_time": "2026-07-13 20:04",
      "stocks": [
        "6182",
        "3374",
        "3211",
        "4958",
        "8150"
      ],
      "comment_count": 4,
      "like_count": 25,
      "laugh_count": 0,
      "money_count": 0,
      "shock_count": 0,
      "think_count": 0,
      "collected_count": 4,
      "url": "https://www.cmoney.tw/forum/article/180720475"
    },
    {
      "id": "180719960",
      "title": "今天🐢闖關失敗，無功而返。 以450為新基準，跌破410就往下買零股。 1股 1...",
      "text": "今天🐢闖關失敗，無功而返。\n\n以450為新基準，跌破410就往下買零股。\n\n1股 1股買，磨耐心\n\n下次噴發時間，我訂在7月底 8月初\n\n逢低買進不吃虧",
      "summary": "今天🐢闖關失敗，無功而返。 以450為新基準，跌破410就往下買零股。 1股 1股買，磨耐心 下次噴發時間，我訂在7月底 8月初 逢低買進不吃虧",
      "time": "2026-07-13 19:32",
      "modify_time": "2026-07-13 19:32",
      "stocks": [
        "3211"
      ],
      "comment_count": 2,
      "like_count": 43,
      "laugh_count": 0,
      "money_count": 0,
      "shock_count": 0,
      "think_count": 0,
      "collected_count": 0,
      "url": "https://www.cmoney.tw/forum/article/180719960"
    },
    {
      "id": "180725004",
      "title": "當沖一日間，漲跌皆修行， 起落不驚心，輸贏見真性。 槓桿借東風，力小撬千斤， 用...",
      "text": "當沖一日間，漲跌皆修行， 起落不驚心，輸贏見真性。 槓桿借東風，力小撬千斤， 用對了方向，山河任縱橫。",
      "summary": "當沖一日間，漲跌皆修行， 起落不驚心，輸贏見真性。 槓桿借東風，力小撬千斤， 用對了方向，山河任縱橫。",
      "time": "2026-07-14 00:47",
      "modify_time": "2026-07-14 00:47",
      "stocks": [
        "8390",
        "2301",
        "2610",
        "2890",
        "2009"
      ],
      "comment_count": 1,
      "like_count": 4,
      "laugh_count": 0,
      "money_count": 0,
      "shock_count": 0,
      "think_count": 0,
      "collected_count": 0,
      "url": "https://www.cmoney.tw/forum/article/180725004"
    },
    {
      "id": "180721656",
      "title": "別隻 這種新聞一定漲停 但阿寶會開高走低 低到去開刀",
      "text": "別隻 這種新聞一定漲停\n但阿寶會開高走低\n低到去開刀",
      "summary": "別隻 這種新聞一定漲停 但阿寶會開高走低 低到去開刀",
      "time": "2026-07-13 21:16",
      "modify_time": "2026-07-13 21:16",
      "stocks": [
        "2301"
      ],
      "comment_count": 2,
      "like_count": 5,
      "laugh_count": 1,
      "money_count": 0,
      "shock_count": 0,
      "think_count": 0,
      "collected_count": 0,
      "url": "https://www.cmoney.tw/forum/article/180721656"
    },
    {
      "id": "180711933",
      "title": "這支232是什麼魔咒 過不去就是過不去",
      "text": "這支232是什麼魔咒 過不去就是過不去",
      "summary": "這支232是什麼魔咒 過不去就是過不去",
      "time": "2026-07-13 13:30",
      "modify_time": "2026-07-13 13:30",
      "stocks": [
        "2301"
      ],
      "comment_count": 6,
      "like_count": 8,
      "laugh_count": 0,
      "money_count": 0,
      "shock_count": 1,
      "think_count": 2,
      "collected_count": 2,
      "url": "https://www.cmoney.tw/forum/article/180711933"
    },
    {
      "id": "180710226",
      "title": "真說不出哪裡怪….價跌量縮",
      "text": "真說不出哪裡怪….價跌量縮",
      "summary": "真說不出哪裡怪….價跌量縮",
      "time": "2026-07-13 12:44",
      "modify_time": "2026-07-13 12:44",
      "stocks": [
        "4931"
      ],
      "comment_count": 2,
      "like_count": 5,
      "laugh_count": 0,
      "money_count": 0,
      "shock_count": 0,
      "think_count": 0,
      "collected_count": 0,
      "url": "https://www.cmoney.tw/forum/article/180710226"
    },
    {
      "id": "180725885",
      "title": "山雨欲來,風滿樓！ 康舒≠康叔=康輸！ 拉高是跑貨用的, 你以為要往上嗎？ 不要...",
      "text": "山雨欲來,風滿樓！\n\n康舒≠康叔=康輸！\n\n拉高是跑貨用的,\n你以為要往上嗎？\n不要傻呼呼分不清！",
      "summary": "山雨欲來,風滿樓！ 康舒≠康叔=康輸！ 拉高是跑貨用的, 你以為要往上嗎？ 不要傻呼呼分不清！",
      "time": "2026-07-14 03:28",
      "modify_time": "2026-07-14 03:28",
      "stocks": [
        "6282"
      ],
      "comment_count": 0,
      "like_count": 2,
      "laugh_count": 0,
      "money_count": 0,
      "shock_count": 0,
      "think_count": 0,
      "collected_count": 0,
      "url": "https://www.cmoney.tw/forum/article/180725885"
    },
    {
      "id": "180725585",
      "title": "融資很勇敢….感恩韭菜們拍拍手…大戶一直出的…你們一直開槓桿買…我等著你們受不了...",
      "text": "融資很勇敢….感恩韭菜們拍拍手…大戶一直出的…你們一直開槓桿買…我等著你們受不了…喔再來慢慢買…還沒還沒…",
      "summary": "融資很勇敢….感恩韭菜們拍拍手…大戶一直出的…你們一直開槓桿買…我等著你們受不了…喔再來慢慢買…還沒還沒…",
      "time": "2026-07-14 02:31",
      "modify_time": "2026-07-14 02:31",
      "stocks": [
        "2308"
      ],
      "comment_count": 0,
      "like_count": 2,
      "laugh_count": 0,
      "money_count": 0,
      "shock_count": 0,
      "think_count": 0,
      "collected_count": 0,
      "url": "https://www.cmoney.tw/forum/article/180725585"
    },
    {
      "id": "180724887",
      "title": "加油！",
      "text": "加油！",
      "summary": "加油！",
      "time": "2026-07-14 00:39",
      "modify_time": "2026-07-14 00:39",
      "stocks": [
        "2301"
      ],
      "comment_count": 0,
      "like_count": 4,
      "laugh_count": 0,
      "money_count": 0,
      "shock_count": 0,
      "think_count": 0,
      "collected_count": 0,
      "url": "https://www.cmoney.tw/forum/article/180724887"
    },
    {
      "id": "180723135",
      "title": "哥哥明天加油嘿⋯",
      "text": "發威操作系能量⋯",
      "summary": "發威操作系能量⋯",
      "time": "2026-07-13 22:20",
      "modify_time": "2026-07-13 22:20",
      "stocks": [
        "2301"
      ],
      "comment_count": 0,
      "like_count": 10,
      "laugh_count": 0,
      "money_count": 0,
      "shock_count": 0,
      "think_count": 0,
      "collected_count": 0,
      "url": "https://www.cmoney.tw/forum/article/180723135"
    },
    {
      "id": "180726025",
      "title": "川普又重新封鎖荷姆茲海峽貨物徵收20%關稅，美股下跌",
      "text": "今天除了蘋果,微軟,亞馬遜三大龍頭上漲之外，其餘股票都下跌\n微軟上漲1.53% 收390.99\n亞馬遜上漲0.8%收247.31\n蘋果上漲0.63% 收317.31\n。\n台積電ADR下跌2.89%收421.58\n海力士ADR下跌9.32%收152.35\n英特爾下跌6.12%收103.12",
      "summary": "今天除了蘋果,微軟,亞馬遜三大龍頭上漲之外，其餘股票都下跌 微軟上漲1.53% 收390.99 亞馬遜上漲0.8%收247.31 蘋果上漲0.63% 收317.31 。 台積電ADR下跌2.89%收421.58 海力士ADR下跌9.32%收152.35 英特爾下跌6.12%收103.12",
      "time": "2026-07-14 04:31",
      "modify_time": "2026-07-14 04:31",
      "stocks": [
        "2303",
        "2408",
        "2308",
        "3481",
        "2330"
      ],
      "comment_count": 0,
      "like_count": 1,
      "laugh_count": 0,
      "money_count": 0,
      "shock_count": 0,
      "think_count": 0,
      "collected_count": 0,
      "url": "https://www.cmoney.tw/forum/article/180726025"
    },
    {
      "id": "180725569",
      "title": "回5日線再彈",
      "text": "回5日線再彈",
      "summary": "回5日線再彈",
      "time": "2026-07-14 02:25",
      "modify_time": "2026-07-14 02:25",
      "stocks": [
        "3211"
      ],
      "comment_count": 0,
      "like_count": 1,
      "laugh_count": 0,
      "money_count": 0,
      "shock_count": 0,
      "think_count": 0,
      "collected_count": 0,
      "url": "https://www.cmoney.tw/forum/article/180725569"
    },
    {
      "id": "180721990",
      "title": "記憶卡蛙加油阿！",
      "text": "阿阿阿阿阿！",
      "summary": "阿阿阿阿阿！",
      "time": "2026-07-13 21:36",
      "modify_time": "2026-07-13 21:36",
      "stocks": [
        "6770",
        "2344",
        "2308"
      ],
      "comment_count": 0,
      "like_count": 13,
      "laugh_count": 0,
      "money_count": 0,
      "shock_count": 1,
      "think_count": 0,
      "collected_count": 0,
      "url": "https://www.cmoney.tw/forum/article/180721990"
    },
    {
      "id": "180720848",
      "title": "未命名文章",
      "text": "",
      "summary": "",
      "time": "2026-07-13 20:26",
      "modify_time": "2026-07-13 20:26",
      "stocks": [
        "3211"
      ],
      "comment_count": 0,
      "like_count": 12,
      "laugh_count": 0,
      "money_count": 0,
      "shock_count": 0,
      "think_count": 0,
      "collected_count": 1,
      "url": "https://www.cmoney.tw/forum/article/180720848"
    },
    {
      "id": "180720815",
      "title": "未命名文章",
      "text": "",
      "summary": "",
      "time": "2026-07-13 20:24",
      "modify_time": "2026-07-13 20:24",
      "stocks": [
        "4931"
      ],
      "comment_count": 0,
      "like_count": 7,
      "laugh_count": 0,
      "money_count": 0,
      "shock_count": 0,
      "think_count": 0,
      "collected_count": 0,
      "url": "https://www.cmoney.tw/forum/article/180720815"
    },
    {
      "id": "180716677",
      "title": "大家想知道這三檔股票是什麼嗎？想知道的留言+1 並追蹤強大",
      "text": "留言100則以上 強大將公佈答案",
      "summary": "留言100則以上 強大將公佈答案",
      "time": "2026-07-13 16:38",
      "modify_time": "2026-07-13 16:38",
      "stocks": [
        "2330",
        "2317",
        "3711",
        "2408",
        "2308"
      ],
      "comment_count": 102,
      "like_count": 87,
      "laugh_count": 0,
      "money_count": 1,
      "shock_count": 0,
      "think_count": 0,
      "collected_count": 4,
      "url": "https://www.cmoney.tw/forum/article/180716677"
    },
    {
      "id": "180716031",
      "title": "在網路上看到有人整理1999年以來的股災 我都經歷過，只是在2019年以前，我的...",
      "text": "在網路上看到有人整理1999年以來的股災\n\n我都經歷過，只是在2019年以前，我的部位不大",
      "summary": "在網路上看到有人整理1999年以來的股災 我都經歷過，只是在2019年以前，我的部位不大",
      "time": "2026-07-13 16:03",
      "modify_time": "2026-07-13 16:03",
      "stocks": [
        "3211"
      ],
      "comment_count": 1,
      "like_count": 17,
      "laugh_count": 0,
      "money_count": 0,
      "shock_count": 0,
      "think_count": 0,
      "collected_count": 4,
      "url": "https://www.cmoney.tw/forum/article/180716031"
    },
    {
      "id": "180715341",
      "title": "AI 沒有熄火，只是市場情緒在波動",
      "text": "市場一直在問：\n\nAI 還行嗎？\n\n看看台積電就知道。\n\n📌 Q2 營收 1.27 兆元\n📌 上半年營收 2.40 兆元\n📌 年增 35.6%\n\n而且分析師普遍預估：\n\n✅ Q3 有望再創歷史新高\n✅ 全年營收成長仍可望超過 30%\n\n台積電還有一個歷史規律：\n\n下半年通常都比上半年更強。\n\n今年又遇上 AI 需求持續超預期，\n代表下半年仍有機會延續高成長。\n\n短線股價會受到資金、利率、情緒影響。\n\n但至少目前看到的基本面是：\n\nAI 沒有熄火，只是市場情緒在波動。\n\n真正值得追蹤的是：\nCoWoS、HBM、GPU、ASIC、資料中心資本支出是否持續增加。\n\n只要需求還在，\nAI 供應鏈的長期邏輯就沒有改變。\n\n#台積電 #AI #半導體 #科技股 #投資 #阿邦AI科技股研究",
      "summary": "市場一直在問： AI 還行嗎？ 看看台積電就知道。 📌 Q2 營收 1.27 兆元 📌 上半年營收 2.40 兆元 📌 年增 35.6% 而且分析師普遍預估： ✅ Q3 有望再創歷史新高 ✅ 全年營收成長仍可望超過 30% 台積電還有一個歷史規律： 下半年通常都比上半年更強。 今年又遇上 AI 需求持續超預期， 代表下...",
      "time": "2026-07-13 15:41",
      "modify_time": "2026-07-13 15:41",
      "stocks": [
        "2330",
        "2308",
        "3017",
        "8299",
        "2408"
      ],
      "comment_count": 1,
      "like_count": 27,
      "laugh_count": 2,
      "money_count": 0,
      "shock_count": 0,
      "think_count": 0,
      "collected_count": 2,
      "url": "https://www.cmoney.tw/forum/article/180715341"
    },
    {
      "id": "180714141",
      "title": "出國了今天忙到沒時間看股 （有人會想我嗎 🤣🤣不要臉ㄧ直問 但好消息ㄧ直來喇！🤣...",
      "text": "出國了今天忙到沒時間看股\n（有人會想我嗎 🤣🤣不要臉ㄧ直問\n但好消息ㄧ直來喇！🤣🤣\n百徽營收創高喇！爽啦！讚🤣🤣\n6220也讚啦！今天開盤特別強勢\n承啟直接鎖喇！哈哈🤣\n台股要走自己的路啦！別受日韓國影響啦！ㄐ8",
      "summary": "出國了今天忙到沒時間看股 （有人會想我嗎 🤣🤣不要臉ㄧ直問 但好消息ㄧ直來喇！🤣🤣 百徽營收創高喇！爽啦！讚🤣🤣 6220也讚啦！今天開盤特別強勢 承啟直接鎖喇！哈哈🤣 台股要走自己的路啦！別受日韓國影響啦！ㄐ8",
      "time": "2026-07-13 15:02",
      "modify_time": "2026-07-13 20:05",
      "stocks": [
        "6259",
        "2425",
        "1810",
        "3704",
        "3323"
      ],
      "comment_count": 16,
      "like_count": 53,
      "laugh_count": 0,
      "money_count": 0,
      "shock_count": 0,
      "think_count": 0,
      "collected_count": 0,
      "url": "https://www.cmoney.tw/forum/article/180714141"
    },
    {
      "id": "180713676",
      "title": "小強 有撐住就好 Q3Q4加油",
      "text": "小強\n\n有撐住就好\n\nQ3Q4加油",
      "summary": "小強 有撐住就好 Q3Q4加油",
      "time": "2026-07-13 14:40",
      "modify_time": "2026-07-13 14:40",
      "stocks": [
        "2392"
      ],
      "comment_count": 6,
      "like_count": 174,
      "laugh_count": 0,
      "money_count": 0,
      "shock_count": 0,
      "think_count": 0,
      "collected_count": 3,
      "url": "https://www.cmoney.tw/forum/article/180713676"
    },
    {
      "id": "180713434",
      "title": "感謝…賞口飯吃..低點再撿！",
      "text": "感謝…賞口飯吃..低點再撿！",
      "summary": "感謝…賞口飯吃..低點再撿！",
      "time": "2026-07-13 14:31",
      "modify_time": "2026-07-13 14:31",
      "stocks": [
        "3211"
      ],
      "comment_count": 0,
      "like_count": 4,
      "laugh_count": 0,
      "money_count": 0,
      "shock_count": 0,
      "think_count": 0,
      "collected_count": 0,
      "url": "https://www.cmoney.tw/forum/article/180713434"
    },
    {
      "id": "180712742",
      "title": "投資or投機？🤡",
      "text": "最近因為投入股市中毒甚深，從前怎不覺得，如今好像時常聽到周遭的人在聊股票。\n今早早餐店隔壁桌的退休阿姨兩個談笑風生，打趣說她買股票個股有賺個三四千就跑，不貪賺個便當錢心態，進進出出，每個禮拜也能賺一萬…慢慢累積….\n我不禁回憶起這一段時間以來，無數次從賺一萬多、四五千，變成只賺幾百、一兩千塊或又住回套房。\n所以我真的是太貪心嗎？選股失敗？\n一直以為投資就長抱，但看著版上朋朋分享，或聽到陌生大媽分享的經驗，蠻常是進進出出的獲利入袋，錢可以像活水一直流動….\n\n當初創見100股抱到帳面曾一萬多，期待著領息兼賺價差，結果也是跟至上一樣往下貼息。不禁想著當初這兩檔各賺一萬多全賣掉其實是最好的選擇，但當下的我會想著哇好不容易有成本優勢還有配息，我怎麼會反著人性去操作呢？\n\n我抱著好久像種菜種花期待茁壯，結果開花了但很快就枯萎🥀了還爛根，不但沒賺到錢還會搞到住套房，難以脫離韭菜命😞🤡",
      "summary": "最近因為投入股市中毒甚深，從前怎不覺得，如今好像時常聽到周遭的人在聊股票。 今早早餐店隔壁桌的退休阿姨兩個談笑風生，打趣說她買股票個股有賺個三四千就跑，不貪賺個便當錢心態，進進出出，每個禮拜也能賺一萬…慢慢累積…. 我不禁回憶起這一段時間以來，無數次從賺一萬多、四五千，變成只賺幾百、一兩千塊或又住回套房。 所以我真的是...",
      "time": "2026-07-13 13:56",
      "modify_time": "2026-07-13 13:56",
      "stocks": [
        "6282",
        "3033",
        "1504",
        "6190",
        "8112"
      ],
      "comment_count": 5,
      "like_count": 19,
      "laugh_count": 0,
      "money_count": 0,
      "shock_count": 0,
      "think_count": 0,
      "collected_count": 0,
      "url": "https://www.cmoney.tw/forum/article/180712742"
    },
    {
      "id": "180708512",
      "title": "1970以上又套到一堆人",
      "text": "1970以上又套到一堆人",
      "summary": "1970以上又套到一堆人",
      "time": "2026-07-13 12:06",
      "modify_time": "2026-07-13 12:06",
      "stocks": [
        "2308"
      ],
      "comment_count": 0,
      "like_count": 6,
      "laugh_count": 0,
      "money_count": 0,
      "shock_count": 0,
      "think_count": 0,
      "collected_count": 0,
      "url": "https://www.cmoney.tw/forum/article/180708512"
    },
    {
      "id": "180706739",
      "title": "什麼時候來一根漲停 等你好久了捏😭",
      "text": "什麼時候來一根漲停 等你好久了捏😭",
      "summary": "什麼時候來一根漲停 等你好久了捏😭",
      "time": "2026-07-13 11:30",
      "modify_time": "2026-07-13 11:30",
      "stocks": [
        "6282"
      ],
      "comment_count": 0,
      "like_count": 8,
      "laugh_count": 1,
      "money_count": 0,
      "shock_count": 0,
      "think_count": 0,
      "collected_count": 0,
      "url": "https://www.cmoney.tw/forum/article/180706739"
    },
    {
      "id": "180704225",
      "title": "6282康舒 早盤大盤和個股反應星期四美國費成指數漲約3% 不久接著又反應美伊戰...",
      "text": "6282康舒\n\n早盤大盤和個股反應星期四美國費成指數漲約3%\n不久接著又反應美伊戰事！？\n價格表現如何就看尾盤收價情形",
      "summary": "6282康舒 早盤大盤和個股反應星期四美國費成指數漲約3% 不久接著又反應美伊戰事！？ 價格表現如何就看尾盤收價情形",
      "time": "2026-07-13 10:35",
      "modify_time": "2026-07-13 10:35",
      "stocks": [
        "6282"
      ],
      "comment_count": 2,
      "like_count": 12,
      "laugh_count": 0,
      "money_count": 0,
      "shock_count": 0,
      "think_count": 0,
      "collected_count": 0,
      "url": "https://www.cmoney.tw/forum/article/180704225"
    },
    {
      "id": "180686981",
      "title": "高力，康舒 股票投資多少參考一下美股BE 線型大概87%像 臺灣重電 東元 一筆...",
      "text": "高力，康舒\n股票投資多少參考一下美股BE\n線型大概87%像\n\n臺灣重電\n東元\n一筆資金在這裡，底層蛋糕都快發霉了！！\n但往往飆股都是曾經擁有\n成本70幾就放著吧\n你那成本90-100的，不要再看我了\n你追高不是我叫你抬轎的！",
      "summary": "高力，康舒 股票投資多少參考一下美股BE 線型大概87%像 臺灣重電 東元 一筆資金在這裡，底層蛋糕都快發霉了！！ 但往往飆股都是曾經擁有 成本70幾就放著吧 你那成本90-100的，不要再看我了 你追高不是我叫你抬轎的！",
      "time": "2026-07-12 03:12",
      "modify_time": "2026-07-12 03:12",
      "stocks": [
        "8996",
        "6282",
        "1504",
        "1513",
        "1519"
      ],
      "comment_count": 30,
      "like_count": 387,
      "laugh_count": 2,
      "money_count": 1,
      "shock_count": 0,
      "think_count": 0,
      "collected_count": 9,
      "url": "https://www.cmoney.tw/forum/article/180686981"
    },
    {
      "id": "180677595",
      "title": "金仁寶～川普乾爹概念股",
      "text": "去年泰國總理要拿「储存右岸外包」去跟美國談對等關稅，哪來底氣？\n\n原來啊….......\n\n老川持倉(圖一）\n第一名：SNDK\n第二名：Dell\n\n2025/Q1 SNDK在F16/1-2F己開始量產ai SSD......他們都知道嘛！\n\nDell 千億大單….仁寶→ccet（Rubin）\n\n2025/Q4 鎧侠～F16/3-4F（Q2投產）\n\n※SanDisk (SNDK) 與鎧俠（Kioxia）是長期緊密的合作夥伴，雙方已合作超過20年，共同開發並製造 NAND Flash 快閃記憶體技術，現在他們上週一起推出最強儲存叫板三星\n\n而Rubin已將液冷列標配\n\n運算、供電、散熱一體化機櫃己量身打造出來（圖）\nQ3確定800V HVDC準時量產，Rubin専用玻璃載板少量供應，6月傳出ccet總部進駐F13…...刺激了！\n\n如果F13是第三座暗黑工廠～那就無敵\n\n可能性很高,因為去年初傳出馬哈差CCAU派了400工程師進駐三廠區，我大概就知道不太單純…....\n\n各位！長期持有他，別沖了！\n前一篇講的泰金寶就是真實且反覆發生的事\n\n就是長期持有他\n\n因為他們一條龍包了！\n※ai產線、殻、櫃、模組、企業SSD、HVDC、液冷(只有晶片、顆粒除外）",
      "summary": "去年泰國總理要拿「储存右岸外包」去跟美國談對等關稅，哪來底氣？ 原來啊…....... 老川持倉(圖一） 第一名：SNDK 第二名：Dell 2025/Q1 SNDK在F16/1-2F己開始量產ai SSD......他們都知道嘛！ Dell 千億大單….仁寶→ccet（Rubin） 2025/Q4 鎧侠～F16/3-...",
      "time": "2026-07-11 01:40",
      "modify_time": "2026-07-11 01:40",
      "stocks": [
        "9105",
        "2324",
        "2312",
        "6282"
      ],
      "comment_count": 11,
      "like_count": 174,
      "laugh_count": 4,
      "money_count": 2,
      "shock_count": 1,
      "think_count": 0,
      "collected_count": 0,
      "url": "https://www.cmoney.tw/forum/article/180677595"
    },
    {
      "id": "180673618",
      "title": "月增年增，營收不是重點了",
      "text": "去年6月森崴能源營收是47.3億.\n\n森崴能源已下市，所以6月營收沒公佈，但從第一季財報可知道，營收組成大致上是3-2期跟富崴電力貢獻，3-2期已經沒認列營收，富崴電力喪失控制權、不能認列營收，所以森崴營收基本上可說是完全沒有，基本上開個1億給他好了。\n\n去年永崴6月51.6億，所以永崴去年本業月營收是：51.6-47.3=4.3億.\n今年6月：7.63-1（粗估）=6.63億\n今年5月：12.9-7.7（森崴5月）=5.2億\n\n去年正崴6月95.6億，所以正崴去年本業月營收是：95.6-51.6=44億.\n今年6月：54.99-7.63=47.36億\n今年5月：60.47-12.91（永崴5月）=47.56億\n\n但這些都不是重點，重點是Q2財報是不是真的認列結束，讓這場公司玩了1年的做帳遊戲徹底結束，（不要再玩我們這些小散戶了，😂😂😂）\n以上資訊僅供參考、謝謝",
      "summary": "去年6月森崴能源營收是47.3億. 森崴能源已下市，所以6月營收沒公佈，但從第一季財報可知道，營收組成大致上是3-2期跟富崴電力貢獻，3-2期已經沒認列營收，富崴電力喪失控制權、不能認列營收，所以森崴營收基本上可說是完全沒有，基本上開個1億給他好了。 去年永崴6月51.6億，所以永崴去年本業月營收是：51.6-47.3...",
      "time": "2026-07-10 18:35",
      "modify_time": "2026-07-10 18:35",
      "stocks": [
        "3712",
        "2392"
      ],
      "comment_count": 2,
      "like_count": 19,
      "laugh_count": 0,
      "money_count": 0,
      "shock_count": 0,
      "think_count": 0,
      "collected_count": 0,
      "url": "https://www.cmoney.tw/forum/article/180673618"
    },
    {
      "id": "180633457",
      "title": "7/8盤後財經台股-1股票",
      "text": "7/8盤後財經台股-1股\n康舒59元\n1795美食209元，7/15醫藥展，雲翔/影片放置於我的社團內\n\n7/8盤後投顧明牌\n2342茂矽53元，整理了一下回至月線，\n3441聯一光69元，整理了一下回至破月線2天，承唐\n8070長華53元，正君\n8932智通119.5元，學進\n\n////7/7盤後財經台股-2\n1717長興77元，新品開始出貨給台積電，目標價100元，宗霖\n4916事欣科107元，\n3689湧德123元，估賺10元，雲翔\n我的補充/去年7.5元，息3.6元，8/3除息，7/28回補\n影片放置於我的社團內\n博大161元，送2.1萬紅包\n\n////(7/5財經台-2股\n博大140元，剛突破整理第一根漲停板，無人機，威元\n3289宜特180元，剛突破整理第一根後小跌回來了，鄭教授，影片放置於社團內\n\n本週7/5在我的公益社團會公告本週精選3-5檔股，週週送萬元紅包\n\n更多選股工具請進入3200人的免費公益社團，具十善心中有一個以上者，詳細的請看十善業道經，菩薩有一法，能斷一切諸惡道苦。此法即十善業道-即永離殺生、偷盜、邪行、妄語、兩舌、惡口、綺語、貪欲、瞋恚、邪見.,\n申請理由\n請寫自己已有\n或是想要有十善業道內容，\n如無寫或是其他感謝文字與空白都會退件可重覆申請，願大家都長養十善心，實修依第八識如來藏真心為本的52位階菩薩道而成在家菩薩，就可以脫離人生輪迴生死苦海，證入常樂我淨涅槃寂靜，具四智圓明，五智三昧，十力，十八不共法而成滿佛果\n阿彌陀佛",
      "summary": "7/8盤後財經台股-1股 康舒59元 1795美食209元，7/15醫藥展，雲翔/影片放置於我的社團內 7/8盤後投顧明牌 2342茂矽53元，整理了一下回至月線， 3441聯一光69元，整理了一下回至破月線2天，承唐 8070長華53元，正君 8932智通119.5元，學進 ////7/7盤後財經台股-2 1717長...",
      "time": "2026-07-09 08:33",
      "modify_time": "2026-07-09 08:33",
      "stocks": [
        "6282",
        "00878",
        "2801",
        "2387",
        "2002"
      ],
      "comment_count": 0,
      "like_count": 26,
      "laugh_count": 0,
      "money_count": 1,
      "shock_count": 0,
      "think_count": 1,
      "collected_count": 0,
      "url": "https://www.cmoney.tw/forum/article/180633457"
    },
    {
      "id": "180431487",
      "title": "GPU什麼時候準備好？",
      "text": "2026/5/11 上午0:00\n許介立接受經報專訪問到\n「康舒發表高壓直流（HVDC）產品，預期新產品何時發酵？」\n回答:HVDC產品現在都在研發階段，要進入量產階段，重點要看GPU什麼時候準備好，我們認為，2027年底到2028年才會開始比較大規模的正式量產。\n「GPU什麼時候準備好」這句是主軸！為何是2027年底到2028年？\n因為只有图片…......是答案！\n\nccet要做三櫃\n1.ai 伺服器整櫃(Q4）\n2.康舒電源櫃(2027-2028）\n3.量子機櫃（Q4測試）\n\n1.3項同時\n2.康舒電源櫃也做好等量產（如照）\n\n金寶股東會訊息沒公開到泰國(封鎖），群創因為玻璃載版漲翻了，金寶封住所有訊息不知道是不是有保密還是保命協議？股價壓制的很好\n\n值得一提的是\n軟銀近期天價併瑞士ABB機器人部門，而康舒2023/7月也正巧併購瑞士ABB美國電源轉換事業部門\n\n瑞士ABB機器人部門也不會比CCET的子公司 CCAU強，只差在CCAU自己沒生產機械手臂(但以前金寶有做）\n\n鎧俠也跑去了F16/3.4層…....\n\n這些是巧合？",
      "summary": "2026/5/11 上午0:00 許介立接受經報專訪問到 「康舒發表高壓直流（HVDC）產品，預期新產品何時發酵？」 回答:HVDC產品現在都在研發階段，要進入量產階段，重點要看GPU什麼時候準備好，我們認為，2027年底到2028年才會開始比較大規模的正式量產。 「GPU什麼時候準備好」這句是主軸！為何是2027年底...",
      "time": "2026-07-06 12:52",
      "modify_time": "2026-07-06 12:52",
      "stocks": [
        "9105",
        "6282",
        "2312"
      ],
      "comment_count": 12,
      "like_count": 118,
      "laugh_count": 2,
      "money_count": 1,
      "shock_count": 1,
      "think_count": 0,
      "collected_count": 2,
      "url": "https://www.cmoney.tw/forum/article/180431487"
    }
  ]
}